firefly/__init__.py
firefly/cli.py
firefly/config.py
firefly/database.py
firefly/logger.py
firefly/routes.py
firefly/services.py
firefly/templates/index.html
firefly_viewer-1.0.4.dist-info/licenses/LICENSE
firefly_viewer-1.0.4.dist-info/METADATA
firefly_viewer-1.0.4.dist-info/WHEEL
firefly_viewer-1.0.4.dist-info/entry_points.txt
firefly_viewer-1.0.4.dist-info/top_level.txt
firefly_viewer-1.0.4.dist-info/RECORD
