Metadata-Version: 2.4
Name: firefly-viewer
Version: 1.0.4
Summary: A web-based viewer for Firefly databases
Home-page: https://gitea.innovativedevsolutions.org/IDSolutions/firefly-viewer
Author: IDSolutions
Author-email: IDSolutions <info@innovativedevsolutions.org>
License: MIT License
Project-URL: Homepage, https://gitea.innovativedevsolutions.org/IDSolutions/firefly-viewer
Project-URL: Documentation, https://gitea.innovativedevsolutions.org/IDSolutions/firefly-viewer#readme
Project-URL: Repository, https://gitea.innovativedevsolutions.org/IDSolutions/firefly-viewer.git
Project-URL: Bug Tracker, https://gitea.innovativedevsolutions.org/IDSolutions/firefly-viewer/issues
Keywords: firefly,database,viewer,web,flask
Classifier: Development Status :: 4 - Beta
Classifier: Environment :: Web Environment
Classifier: Framework :: Flask
Classifier: Intended Audience :: Developers
Classifier: License :: OSI Approved :: MIT License
Classifier: Operating System :: OS Independent
Classifier: Programming Language :: Python :: 3
Classifier: Programming Language :: Python :: 3.13
Classifier: Topic :: Database :: Front-Ends
Requires-Python: >=3.13
License-File: LICENSE
Requires-Dist: Flask
Requires-Dist: redis
Requires-Dist: python-dotenv
Requires-Dist: ifireflylib
Requires-Dist: click
Requires-Dist: waitress
Dynamic: author
Dynamic: home-page
Dynamic: license-file
Dynamic: requires-python
